{
  "stocks": {
    "1": {
      "recent": [
        1164.88,
        1164.61,
        1164.47,
        1164.67,
        1164.74,
        1164.76,
        1164.59,
        1164.76,
        1164.8,
        1164.73,
        1164.8,
        1164.85,
        1164.66,
        1164.58,
        1164.28,
        1164.25,
        1164.24,
        1163.99,
        1164.32,
        1164.39,
        1164.26,
        1164.1,
        1164.12,
        1164.1,
        1164.19,
        1164.31,
        1164.29,
        1164.29,
        1164.4,
        1164.44,
        1164.42,
        1164.29,
        1164.45,
        1164.86,
        1164.96,
        1165.72,
        1166.05,
        1166.01,
        1166.09,
        1166.14,
        1166.12,
        1166.12,
        1166.39,
        1166.39,
        1166.39,
        1166.44,
        1166.56,
        1166.57,
        1166.61,
        1166.47,
        1166.43,
        1166.41,
        1166.45,
        1166.16,
        1166.59,
        1166.73,
        1166.69,
        1166.55,
        1166.52,
        1166.64,
        1166.39,
        1166.35,
        1166.42,
        1166.17,
        1166.3,
        1166.31,
        1166.35,
        1166.27,
        1166.37,
        1166.49,
        1166.35,
        1166.28,
        1166.6,
        1166.58,
        1166.64,
        1166.96,
        1166.87,
        1166.83,
        1166.84,
        1166.81,
        1167.3,
        1167.08,
        1167.36,
        1167.47,
        1167.36,
        1167.45,
        1167.45,
        1167.26,
        1167.28,
        1167.15,
        1167.07,
        1167.16,
        1167.17,
        1167.05,
        1167.31,
        1167.19,
        1167.19,
        1167.06,
        1167.11,
        1167.05,
        1166.93,
        1166.89,
        1167.11,
        1167.33,
        1167.15,
        1167.34,
        1167.36,
        1167.4,
        1167.56,
        1167.42,
        1167.42,
        1167.54,
        1167.3,
        1167.11,
        1167.06,
        1166.9,
        1166.97,
        1166.62,
        1166.68,
        1166.64
      ],
      "dayLow": 1160.88,
      "dayHigh": 1167.56,
      "weekLow": 1160.88,
      "weekHigh": 1167.56,
      "allTimeLow": 1160.88,
      "allTimeHigh": 1167.56
    },
    "2": {
      "recent": [
        1186.09,
        1186.32,
        1186.16,
        1186.32,
        1186.36,
        1186.34,
        1186.42,
        1186.24,
        1186.27,
        1186.42,
        1186.35,
        1186.62,
        1186.85,
        1186.72,
        1186.88,
        1186.9,
        1186.93,
        1187.33,
        1187.3,
        1187.38,
        1187.44,
        1187.49,
        1187.34,
        1187.49,
        1187.91,
        1187.84,
        1187.84,
        1187.74,
        1187.81,
        1188.04,
        1188.79,
        1188.89,
        1188.64,
        1188.29,
        1188.04,
        1187.74,
        1187.97,
        1187.97,
        1188.04,
        1187.99,
        1188.07,
        1188.04,
        1188,
        1187.92,
        1188,
        1187.9,
        1187.97,
        1187.8,
        1188.02,
        1188.67,
        1188.65,
        1188.72,
        1188.72,
        1188.87,
        1188.85,
        1189,
        1188.95,
        1189.02,
        1188.82,
        1188.75,
        1188.87,
        1188.9,
        1189.02,
        1188.94,
        1189.27,
        1189.2,
        1189.17,
        1189.25,
        1189.67,
        1189.7,
        1189.62,
        1189.7,
        1189.6,
        1189.65,
        1189.6,
        1189.77,
        1189.8,
        1189.65,
        1189.73,
        1190.2,
        1190.58,
        1190.68,
        1190.38,
        1190.23,
        1190.31,
        1190.31,
        1190.25,
        1190.23,
        1190.45,
        1190.38,
        1190.23,
        1190.28,
        1190.35,
        1190.21,
        1190.21,
        1190.15,
        1190.28,
        1190.31,
        1190.21,
        1190.38,
        1190.73,
        1191.03,
        1191.15,
        1191.15,
        1191.43,
        1191.28,
        1191.3,
        1191.3,
        1191.35,
        1191.4,
        1191.4,
        1191.35,
        1190.83,
        1190.83,
        1190.8,
        1190.3,
        1190.15,
        1190.3,
        1190.35,
        1190.4
      ],
      "dayLow": 1186.02,
      "dayHigh": 1193.52,
      "weekLow": 1186.02,
      "weekHigh": 1193.52,
      "allTimeLow": 1186.02,
      "allTimeHigh": 1193.52
    },
    "3": {
      "recent": [
        676.56,
        676.55,
        676.53,
        676.51,
        676.52,
        676.65,
        676.67,
        676.64,
        676.67,
        676.6,
        676.6,
        676.65,
        676.53,
        676.63,
        676.6,
        676.68,
        676.73,
        676.7,
        676.69,
        676.73,
        676.59,
        676.5,
        676.48,
        676.32,
        676.28,
        676.27,
        676.21,
        676.17,
        676.12,
        676.04,
        676.18,
        676.18,
        676.25,
        676.27,
        676.3,
        676.26,
        676.21,
        676.19,
        676.12,
        676.21,
        676.45,
        676.53,
        676.59,
        676.58,
        676.67,
        676.67,
        676.62,
        676.68,
        676.6,
        676.69,
        676.63,
        676.64,
        676.64,
        676.82,
        676.86,
        677.02,
        676.95,
        676.91,
        677.08,
        677.07,
        677.1,
        677.1,
        677.13,
        677.19,
        677.11,
        677.18,
        677.22,
        677.26,
        677.3,
        677.4,
        677.42,
        677.28,
        677.33,
        677.41,
        677.47,
        677.34,
        677.52,
        677.51,
        677.72,
        677.6,
        677.73,
        677.78,
        677.91,
        678,
        678.04,
        678.14,
        678.32,
        678.4,
        678.51,
        678.5,
        678.56,
        678.59,
        678.47,
        678.66,
        678.69,
        678.72,
        678.71,
        678.63,
        678.57,
        678.49,
        678.61,
        678.63,
        678.76,
        678.69,
        678.75,
        678.77,
        678.77,
        678.94,
        679.05,
        679.09,
        678.89,
        678.85,
        678.96,
        679.11,
        679.15,
        679.13,
        679.22,
        678.88,
        678.91,
        678.91
      ],
      "dayLow": 675.27,
      "dayHigh": 679.22,
      "weekLow": 675.27,
      "weekHigh": 679.22,
      "allTimeLow": 675.27,
      "allTimeHigh": 679.22
    },
    "4": {
      "recent": [
        447.1,
        447.08,
        447.1,
        447.08,
        447.13,
        447.09,
        447.18,
        447.22,
        447.35,
        447.14,
        447.16,
        447.21,
        446.97,
        447.01,
        446.95,
        446.93,
        447.01,
        447.01,
        447.06,
        447,
        447.01,
        447.03,
        447.11,
        447.04,
        447.22,
        447.31,
        447.27,
        447.22,
        447.39,
        447.31,
        447.34,
        447.3,
        447.35,
        447.23,
        447.21,
        447.21,
        447.25,
        447.1,
        447.19,
        447.19,
        447.15,
        447.3,
        447.27,
        447.24,
        447.2,
        447.21,
        447.19,
        447.23,
        447.2,
        447.18,
        447.2,
        447.18,
        447.12,
        447.12,
        447.15,
        447.18,
        447.12,
        447.15,
        447.14,
        447.09,
        447.07,
        447.12,
        447.12,
        446.99,
        446.88,
        446.8,
        446.83,
        446.87,
        446.87,
        446.99,
        446.83,
        446.75,
        446.82,
        446.9,
        446.83,
        446.85,
        446.79,
        446.75,
        446.63,
        446.54,
        446.58,
        446.47,
        446.49,
        446.46,
        446.41,
        446.46,
        446.47,
        446.47,
        446.59,
        446.56,
        446.49,
        446.54,
        446.66,
        446.75,
        446.75,
        446.76,
        446.76,
        446.73,
        446.77,
        446.71,
        446.69,
        446.69,
        446.66,
        446.66,
        446.67,
        446.69,
        446.75,
        446.75,
        446.73,
        446.8,
        446.78,
        446.6,
        446.67,
        446.67,
        446.75,
        446.65,
        446.6,
        446.6,
        446.6,
        446.62
      ],
      "dayLow": 446.41,
      "dayHigh": 449.79,
      "weekLow": 446.41,
      "weekHigh": 450.64,
      "allTimeLow": 446.41,
      "allTimeHigh": 450.64
    },
    "5": {
      "recent": [
        181.78,
        181.81,
        181.85,
        181.88,
        181.92,
        181.91,
        181.94,
        181.96,
        181.95,
        181.96,
        181.96,
        181.95,
        182.01,
        182.03,
        182.09,
        182.03,
        181.97,
        182.03,
        182.04,
        181.98,
        182.04,
        182.07,
        182.01,
        182,
        181.92,
        181.92,
        181.85,
        181.88,
        181.87,
        181.86,
        181.84,
        181.87,
        181.86,
        181.86,
        181.86,
        181.88,
        181.88,
        181.92,
        181.93,
        181.9,
        181.89,
        181.87,
        181.86,
        181.89,
        181.87,
        181.86,
        181.87,
        181.9,
        181.85,
        181.79,
        181.79,
        181.79,
        181.76,
        181.78,
        181.81,
        181.85,
        181.88,
        181.94,
        181.89,
        181.93,
        181.89,
        181.9,
        181.88,
        181.9,
        181.92,
        181.97,
        181.98,
        182.05,
        182.05,
        182.09,
        182.05,
        182.02,
        182.03,
        182.04,
        182.08,
        182.1,
        182.1,
        182.11,
        182.13,
        182.13,
        182.14,
        182.08,
        182.11,
        182.09,
        182.08,
        182.11,
        182.08,
        182.06,
        182.1,
        182.08,
        182.08,
        182.06,
        182.05,
        182.03,
        181.98,
        181.99,
        181.98,
        181.97,
        182,
        182,
        182.02,
        182.03,
        182.03,
        182.04,
        182.06,
        182.06,
        182.06,
        182.03,
        182.03,
        182.03,
        182.04,
        182.02,
        182.02,
        182,
        181.99,
        182.01,
        181.95,
        181.95,
        181.96,
        181.98
      ],
      "dayLow": 181.09,
      "dayHigh": 182.14,
      "weekLow": 180.88,
      "weekHigh": 182.14,
      "allTimeLow": 180.88,
      "allTimeHigh": 182.14
    },
    "6": {
      "recent": [
        303.43,
        303.51,
        303.51,
        303.48,
        303.44,
        303.48,
        303.5,
        303.56,
        303.51,
        303.48,
        303.44,
        303.48,
        303.53,
        303.51,
        303.45,
        303.47,
        303.45,
        303.45,
        303.47,
        303.46,
        303.5,
        303.54,
        303.5,
        303.5,
        303.51,
        303.49,
        303.49,
        303.51,
        303.51,
        303.52,
        303.55,
        303.55,
        303.57,
        303.58,
        303.56,
        303.56,
        303.57,
        303.56,
        303.54,
        303.51,
        303.58,
        303.55,
        303.53,
        303.55,
        303.58,
        303.56,
        303.59,
        303.6,
        303.62,
        303.61,
        303.59,
        303.58,
        303.55,
        303.55,
        303.59,
        303.53,
        303.54,
        303.54,
        303.51,
        303.5,
        303.47,
        303.51,
        303.49,
        303.49,
        303.51,
        303.53,
        303.47,
        303.45,
        303.48,
        303.49,
        303.5,
        303.49,
        303.49,
        303.5,
        303.49,
        303.5,
        303.5,
        303.5,
        303.47,
        303.48,
        303.53,
        303.52,
        303.51,
        303.51,
        303.51,
        303.5,
        303.54,
        303.52,
        303.5,
        303.51,
        303.53,
        303.52,
        303.52,
        303.5,
        303.47,
        303.49,
        303.5,
        303.49,
        303.49,
        303.53,
        303.5,
        303.53,
        303.55,
        303.53,
        303.6,
        303.61,
        303.59,
        303.59,
        303.63,
        303.66,
        303.63,
        303.61,
        303.63,
        303.64,
        303.63,
        303.65,
        303.64,
        303.66,
        303.65,
        303.68
      ],
      "dayLow": 301.64,
      "dayHigh": 303.68,
      "weekLow": 301.27,
      "weekHigh": 303.68,
      "allTimeLow": 301.27,
      "allTimeHigh": 303.68
    },
    "7": {
      "recent": [
        389.64,
        389.61,
        389.72,
        389.67,
        389.63,
        389.72,
        389.8,
        389.65,
        389.58,
        389.64,
        389.59,
        389.65,
        389.51,
        389.55,
        389.5,
        389.49,
        389.53,
        389.49,
        389.69,
        389.89,
        389.85,
        389.89,
        389.98,
        389.92,
        389.93,
        390.01,
        389.96,
        389.95,
        389.89,
        389.89,
        389.9,
        389.95,
        390,
        389.98,
        390,
        389.98,
        390,
        389.97,
        389.91,
        389.92,
        389.97,
        389.93,
        389.86,
        389.87,
        389.85,
        389.87,
        389.83,
        389.91,
        389.92,
        389.89,
        389.9,
        389.88,
        389.9,
        389.87,
        389.89,
        389.85,
        389.81,
        389.78,
        389.78,
        389.77,
        389.86,
        389.87,
        389.9,
        389.9,
        389.96,
        389.99,
        389.99,
        389.99,
        390.02,
        390,
        389.98,
        389.9,
        389.93,
        389.99,
        389.79,
        389.77,
        389.83,
        389.82,
        389.78,
        389.84,
        389.86,
        389.86,
        389.87,
        389.87,
        389.91,
        389.87,
        389.85,
        389.89,
        389.86,
        389.8,
        389.77,
        389.87,
        389.9,
        389.9,
        389.92,
        389.94,
        389.9,
        389.91,
        389.92,
        389.96,
        389.94,
        389.9,
        389.81,
        389.84,
        389.85,
        389.84,
        389.89,
        389.95,
        389.95,
        389.94,
        389.95,
        389.95,
        389.99,
        390,
        390.03,
        390.02,
        390.06,
        390.02,
        389.97,
        389.92
      ],
      "dayLow": 389.4,
      "dayHigh": 390.91,
      "weekLow": 389.4,
      "weekHigh": 390.91,
      "allTimeLow": 389.4,
      "allTimeHigh": 390.91
    },
    "8": {
      "recent": [
        54.52,
        54.51,
        54.52,
        54.52,
        54.51,
        54.52,
        54.52,
        54.52,
        54.52,
        54.52,
        54.53,
        54.52,
        54.52,
        54.52,
        54.51,
        54.51,
        54.51,
        54.52,
        54.51,
        54.5,
        54.5,
        54.49,
        54.5,
        54.49,
        54.49,
        54.48,
        54.48,
        54.47,
        54.48,
        54.47,
        54.47,
        54.46,
        54.46,
        54.46,
        54.45,
        54.46,
        54.46,
        54.46,
        54.45,
        54.46,
        54.47,
        54.47,
        54.47,
        54.47,
        54.47,
        54.47,
        54.47,
        54.47,
        54.48,
        54.47,
        54.47,
        54.47,
        54.47,
        54.47,
        54.48,
        54.48,
        54.48,
        54.48,
        54.48,
        54.5,
        54.5,
        54.49,
        54.49,
        54.49,
        54.51,
        54.5,
        54.48,
        54.48,
        54.48,
        54.5,
        54.48,
        54.48,
        54.48,
        54.48,
        54.48,
        54.48,
        54.48,
        54.48,
        54.48,
        54.47,
        54.47,
        54.47,
        54.49,
        54.49,
        54.49,
        54.49,
        54.48,
        54.48,
        54.48,
        54.47,
        54.46,
        54.47,
        54.47,
        54.47,
        54.47,
        54.47,
        54.46,
        54.46,
        54.46,
        54.46,
        54.47,
        54.47,
        54.48,
        54.47,
        54.45,
        54.45,
        54.45,
        54.45,
        54.44,
        54.45,
        54.44,
        54.43,
        54.43,
        54.41,
        54.41,
        54.4,
        54.4,
        54.4,
        54.4,
        54.41
      ],
      "dayLow": 54.39,
      "dayHigh": 54.71,
      "weekLow": 54.39,
      "weekHigh": 54.71,
      "allTimeLow": 54.39,
      "allTimeHigh": 54.71
    },
    "9": {
      "recent": [
        309.36,
        309.41,
        309.41,
        309.48,
        309.45,
        309.41,
        309.45,
        309.46,
        309.4,
        309.44,
        309.43,
        309.45,
        309.41,
        309.39,
        309.38,
        309.42,
        309.4,
        309.34,
        309.37,
        309.43,
        309.4,
        309.44,
        309.47,
        309.44,
        309.47,
        309.49,
        309.47,
        309.52,
        309.57,
        309.6,
        309.61,
        309.52,
        309.55,
        309.59,
        309.55,
        309.56,
        309.56,
        309.51,
        309.48,
        309.47,
        309.44,
        309.43,
        309.42,
        309.44,
        309.46,
        309.46,
        309.54,
        309.54,
        309.51,
        309.46,
        309.48,
        309.43,
        309.42,
        309.41,
        309.42,
        309.41,
        309.4,
        309.37,
        309.32,
        309.35,
        309.36,
        309.41,
        309.27,
        309.37,
        309.33,
        309.35,
        309.4,
        309.4,
        309.41,
        309.38,
        309.42,
        309.38,
        309.39,
        309.37,
        309.35,
        309.33,
        309.32,
        309.34,
        309.4,
        309.4,
        309.43,
        309.44,
        309.41,
        309.37,
        309.36,
        309.33,
        309.36,
        309.34,
        309.27,
        309.28,
        309.28,
        309.31,
        309.36,
        309.4,
        309.4,
        309.34,
        309.34,
        309.32,
        309.3,
        309.25,
        309.27,
        309.26,
        309.27,
        309.24,
        309.23,
        309.23,
        309.2,
        309.27,
        309.19,
        309.23,
        309.26,
        309.26,
        309.26,
        309.16,
        309.11,
        309.12,
        309.09,
        309.09,
        309.09,
        309.05
      ],
      "dayLow": 309.05,
      "dayHigh": 310.89,
      "weekLow": 309.05,
      "weekHigh": 310.91,
      "allTimeLow": 309.05,
      "allTimeHigh": 310.91
    },
    "10": {
      "recent": [
        887.32,
        887.35,
        887.3,
        887.33,
        887.28,
        887.29,
        887.36,
        887.38,
        887.4,
        887.48,
        887.4,
        887.45,
        887.38,
        887.31,
        887.36,
        887.33,
        887.38,
        887.24,
        887.19,
        887.33,
        887.36,
        887.31,
        887.33,
        887.4,
        887.36,
        887.45,
        887.28,
        887.31,
        887.33,
        887.26,
        887.34,
        887.31,
        887.46,
        887.54,
        887.44,
        887.59,
        887.56,
        887.63,
        887.48,
        887.71,
        887.68,
        887.73,
        887.85,
        887.88,
        887.9,
        888.02,
        888.15,
        888.13,
        887.98,
        887.82,
        887.92,
        887.93,
        887.87,
        887.85,
        887.73,
        887.7,
        887.95,
        887.97,
        888.08,
        888.1,
        888.12,
        888.04,
        888.02,
        888.17,
        888.07,
        888.12,
        888.23,
        888.1,
        888.07,
        888.02,
        888.1,
        888.17,
        888.32,
        888.17,
        888.27,
        888.34,
        888.44,
        888.49,
        888.54,
        888.52,
        888.69,
        888.77,
        888.61,
        888.72,
        888.77,
        888.79,
        888.72,
        888.71,
        888.76,
        888.77,
        888.79,
        888.61,
        888.64,
        888.76,
        888.48,
        888.56,
        888.21,
        888.29,
        888.22,
        888.25,
        888.19,
        887.58,
        887.68,
        887.38,
        887.17,
        886.98,
        887.15,
        887.23,
        887.7,
        887.63,
        887.33,
        887.25,
        887.38,
        887.51,
        887.51,
        886.81,
        886.77,
        886.37,
        886.37,
        886.58
      ],
      "dayLow": 883.37,
      "dayHigh": 888.79,
      "weekLow": 883,
      "weekHigh": 888.79,
      "allTimeLow": 883,
      "allTimeHigh": 888.79
    },
    "11": {
      "recent": [
        279.68,
        279.68,
        279.62,
        279.64,
        279.64,
        279.68,
        279.68,
        279.58,
        279.54,
        279.54,
        279.5,
        279.48,
        279.43,
        279.5,
        279.56,
        279.49,
        279.5,
        279.49,
        279.51,
        279.58,
        279.49,
        279.56,
        279.56,
        279.54,
        279.47,
        279.49,
        279.62,
        279.52,
        279.35,
        279.34,
        279.27,
        279.3,
        279.27,
        279.29,
        279.23,
        279.25,
        279.23,
        279.23,
        279.19,
        279.21,
        279.18,
        279.11,
        279.19,
        279.22,
        279.09,
        279.03,
        279.03,
        279.02,
        278.9,
        278.86,
        278.87,
        278.87,
        278.89,
        278.87,
        278.82,
        278.92,
        279.03,
        279.08,
        279.08,
        279.02,
        279.1,
        279.13,
        279.14,
        279.14,
        279.08,
        279,
        279,
        278.95,
        278.99,
        278.91,
        278.84,
        278.85,
        278.88,
        278.85,
        278.83,
        278.77,
        278.86,
        278.84,
        278.87,
        278.8,
        278.73,
        278.72,
        278.73,
        278.79,
        278.88,
        278.9,
        278.94,
        278.91,
        278.87,
        278.95,
        278.93,
        278.95,
        278.95,
        278.95,
        278.99,
        279.13,
        279.09,
        279.05,
        279.05,
        279.06,
        278.95,
        278.96,
        278.92,
        278.89,
        278.82,
        278.79,
        278.8,
        278.8,
        278.74,
        278.79,
        278.84,
        278.91,
        278.92,
        278.98,
        278.96,
        278.94,
        278.97,
        279.04,
        279,
        279.02
      ],
      "dayLow": 278.72,
      "dayHigh": 281.1,
      "weekLow": 278.72,
      "weekHigh": 281.13,
      "allTimeLow": 278.72,
      "allTimeHigh": 281.13
    },
    "12": {
      "recent": [
        229.32,
        229.34,
        229.31,
        229.31,
        229.25,
        229.28,
        229.35,
        229.33,
        229.32,
        229.38,
        229.35,
        229.37,
        229.41,
        229.42,
        229.43,
        229.44,
        229.45,
        229.42,
        229.45,
        229.47,
        229.4,
        229.43,
        229.43,
        229.51,
        229.44,
        229.36,
        229.37,
        229.4,
        229.38,
        229.4,
        229.4,
        229.43,
        229.44,
        229.41,
        229.41,
        229.41,
        229.34,
        229.37,
        229.36,
        229.36,
        229.36,
        229.35,
        229.34,
        229.34,
        229.35,
        229.37,
        229.41,
        229.37,
        229.36,
        229.43,
        229.45,
        229.45,
        229.43,
        229.43,
        229.42,
        229.41,
        229.41,
        229.41,
        229.41,
        229.41,
        229.38,
        229.36,
        229.36,
        229.35,
        229.34,
        229.32,
        229.3,
        229.33,
        229.36,
        229.29,
        229.23,
        229.22,
        229.17,
        229.17,
        229.16,
        229.14,
        229.16,
        229.14,
        229.17,
        229.21,
        229.22,
        229.23,
        229.26,
        229.23,
        229.23,
        229.26,
        229.23,
        229.21,
        229.26,
        229.31,
        229.31,
        229.32,
        229.36,
        229.37,
        229.41,
        229.43,
        229.43,
        229.45,
        229.5,
        229.53,
        229.46,
        229.48,
        229.47,
        229.48,
        229.52,
        229.52,
        229.51,
        229.54,
        229.56,
        229.58,
        229.52,
        229.51,
        229.53,
        229.54,
        229.51,
        229.51,
        229.56,
        229.52,
        229.53,
        229.51
      ],
      "dayLow": 228.96,
      "dayHigh": 229.58,
      "weekLow": 228.47,
      "weekHigh": 229.58,
      "allTimeLow": 228.47,
      "allTimeHigh": 229.58
    },
    "13": {
      "recent": [
        526.04,
        526.1,
        526.01,
        525.92,
        525.98,
        526.01,
        526.07,
        526.08,
        526.04,
        526.06,
        526.06,
        526.15,
        526.2,
        526.2,
        526.29,
        526.28,
        526.29,
        526.32,
        526.41,
        526.41,
        526.36,
        526.5,
        526.53,
        526.59,
        526.62,
        526.68,
        526.56,
        526.61,
        526.85,
        527,
        527.05,
        527.23,
        527.27,
        527.41,
        527.51,
        527.47,
        527.5,
        527.55,
        527.58,
        527.7,
        527.61,
        527.55,
        527.78,
        527.68,
        527.77,
        527.63,
        527.66,
        527.67,
        527.59,
        527.56,
        527.63,
        527.5,
        527.57,
        527.39,
        527.36,
        527.61,
        527.56,
        527.6,
        527.67,
        527.69,
        527.66,
        527.64,
        527.69,
        527.82,
        527.71,
        527.71,
        527.62,
        527.68,
        527.63,
        527.63,
        527.64,
        527.66,
        527.72,
        527.81,
        527.82,
        527.87,
        527.83,
        527.81,
        527.87,
        527.94,
        528.02,
        527.98,
        528.08,
        528.12,
        528.03,
        527.96,
        527.93,
        527.84,
        527.87,
        527.86,
        527.92,
        527.9,
        527.89,
        527.88,
        527.89,
        527.88,
        527.91,
        527.77,
        527.8,
        527.84,
        527.84,
        527.93,
        527.95,
        527.98,
        527.97,
        527.95,
        527.86,
        527.86,
        527.83,
        527.84,
        527.98,
        527.92,
        527.83,
        527.83,
        527.8,
        527.84,
        527.83,
        527.8,
        527.83,
        527.78
      ],
      "dayLow": 525.01,
      "dayHigh": 528.58,
      "weekLow": 525.01,
      "weekHigh": 528.58,
      "allTimeLow": 525.01,
      "allTimeHigh": 528.58
    },
    "14": {
      "recent": [
        131.49,
        131.48,
        131.52,
        131.52,
        131.54,
        131.55,
        131.55,
        131.55,
        131.55,
        131.54,
        131.57,
        131.57,
        131.58,
        131.59,
        131.55,
        131.57,
        131.54,
        131.52,
        131.52,
        131.53,
        131.52,
        131.49,
        131.5,
        131.44,
        131.44,
        131.44,
        131.46,
        131.47,
        131.48,
        131.45,
        131.45,
        131.46,
        131.47,
        131.49,
        131.52,
        131.54,
        131.54,
        131.52,
        131.53,
        131.53,
        131.56,
        131.59,
        131.57,
        131.55,
        131.55,
        131.52,
        131.55,
        131.54,
        131.56,
        131.55,
        131.55,
        131.54,
        131.53,
        131.52,
        131.53,
        131.54,
        131.55,
        131.53,
        131.55,
        131.55,
        131.54,
        131.55,
        131.55,
        131.52,
        131.51,
        131.51,
        131.51,
        131.51,
        131.5,
        131.51,
        131.5,
        131.5,
        131.48,
        131.48,
        131.51,
        131.52,
        131.5,
        131.5,
        131.5,
        131.51,
        131.5,
        131.49,
        131.49,
        131.5,
        131.51,
        131.52,
        131.51,
        131.5,
        131.51,
        131.52,
        131.5,
        131.48,
        131.49,
        131.5,
        131.5,
        131.54,
        131.5,
        131.5,
        131.49,
        131.51,
        131.5,
        131.52,
        131.49,
        131.5,
        131.53,
        131.5,
        131.49,
        131.45,
        131.43,
        131.44,
        131.42,
        131.42,
        131.43,
        131.44,
        131.43,
        131.42,
        131.43,
        131.43,
        131.44,
        131.44
      ],
      "dayLow": 131.27,
      "dayHigh": 131.76,
      "weekLow": 131.26,
      "weekHigh": 132.09,
      "allTimeLow": 131.26,
      "allTimeHigh": 132.09
    },
    "15": {
      "recent": [
        843.1,
        843.02,
        842.99,
        843,
        843.13,
        843.05,
        843.12,
        843.11,
        843.13,
        843.17,
        843.03,
        843.06,
        843.09,
        843.1,
        842.98,
        842.97,
        843.05,
        843.13,
        843.15,
        843.16,
        843.09,
        843.1,
        843.13,
        843.04,
        843.14,
        843.1,
        843.13,
        843.13,
        843.36,
        843.22,
        843.23,
        843.33,
        843.14,
        843.07,
        843.07,
        843.01,
        842.93,
        843.02,
        843.13,
        843.02,
        842.87,
        842.84,
        842.86,
        842.62,
        842.52,
        842.69,
        842.69,
        842.69,
        842.54,
        842.7,
        842.8,
        842.79,
        842.7,
        842.52,
        842.62,
        842.64,
        842.65,
        842.43,
        842.42,
        842.52,
        842.26,
        842.18,
        842.44,
        842.47,
        842.49,
        842.39,
        842.49,
        842.49,
        842.79,
        842.79,
        842.82,
        842.9,
        842.89,
        842.87,
        842.85,
        842.79,
        842.87,
        842.92,
        842.93,
        842.97,
        842.99,
        842.99,
        842.98,
        842.9,
        842.91,
        842.74,
        842.69,
        842.78,
        842.79,
        842.69,
        842.82,
        842.81,
        842.82,
        842.71,
        842.74,
        842.66,
        842.65,
        842.61,
        842.53,
        842.54,
        842.52,
        842.49,
        842.5,
        842.64,
        842.64,
        842.56,
        842.6,
        842.58,
        842.51,
        842.62,
        842.61,
        842.62,
        842.59,
        842.62,
        842.61,
        842.67,
        842.69,
        842.73,
        842.55,
        842.54
      ],
      "dayLow": 842.18,
      "dayHigh": 846.5,
      "weekLow": 842.13,
      "weekHigh": 846.5,
      "allTimeLow": 842.13,
      "allTimeHigh": 846.5
    },
    "16": {
      "recent": [
        695.8,
        695.74,
        695.86,
        695.76,
        695.74,
        695.56,
        695.61,
        695.55,
        695.82,
        695.88,
        695.98,
        696.08,
        696.22,
        696.23,
        696.11,
        696.07,
        696.07,
        696.03,
        696.01,
        696.11,
        696.35,
        696.36,
        696.31,
        696.52,
        696.53,
        696.53,
        696.4,
        696.53,
        696.43,
        696.5,
        696.59,
        696.76,
        696.87,
        696.71,
        696.73,
        696.77,
        696.82,
        696.73,
        696.71,
        696.58,
        696.76,
        696.7,
        696.96,
        696.85,
        696.84,
        696.87,
        696.87,
        697,
        696.89,
        696.84,
        696.88,
        696.86,
        696.78,
        696.94,
        697.02,
        696.95,
        696.94,
        697.19,
        697.21,
        697.3,
        697.26,
        697.45,
        697.51,
        697.57,
        697.64,
        697.68,
        697.62,
        697.5,
        697.52,
        697.66,
        697.68,
        697.74,
        697.5,
        697.56,
        697.58,
        697.55,
        697.5,
        697.35,
        697.3,
        697.21,
        697.17,
        697.16,
        697.24,
        697.37,
        697.27,
        697.31,
        697.14,
        697.12,
        697.13,
        697.06,
        697.07,
        696.83,
        696.81,
        696.78,
        696.91,
        696.93,
        697.01,
        697.11,
        697.28,
        697.42,
        697.28,
        697.34,
        697.33,
        697.47,
        697.56,
        697.58,
        697.48,
        697.27,
        697.39,
        697.51,
        697.68,
        697.66,
        697.79,
        697.77,
        697.86,
        697.86,
        697.8,
        697.79,
        697.89,
        697.8
      ],
      "dayLow": 693.66,
      "dayHigh": 697.89,
      "weekLow": 693.24,
      "weekHigh": 697.89,
      "allTimeLow": 693.24,
      "allTimeHigh": 697.89
    },
    "17": {
      "recent": [
        576.49,
        576.19,
        576.37,
        576.4,
        576.4,
        576.38,
        576.35,
        576.33,
        576.33,
        576.33,
        576.35,
        576.05,
        576.04,
        576.04,
        576.21,
        576.23,
        576.15,
        576.16,
        576.27,
        576.28,
        576.26,
        576.14,
        576.15,
        576.17,
        576.23,
        576.21,
        576.23,
        576.2,
        576.21,
        576.23,
        576.28,
        576.17,
        576.15,
        576.15,
        576.13,
        576.12,
        576.11,
        576.11,
        576.14,
        576.17,
        576.16,
        576.16,
        576.17,
        576.14,
        576.11,
        576.15,
        576.01,
        576.17,
        576.15,
        576.07,
        576.11,
        576.11,
        576.12,
        576.09,
        576.22,
        576.12,
        576.1,
        576.1,
        576.13,
        576.14,
        576.13,
        576.26,
        576.23,
        576.21,
        576.2,
        576.19,
        576.17,
        576.19,
        575.86,
        575.96,
        575.96,
        575.98,
        576.25,
        576.25,
        576.23,
        576.23,
        576,
        576.38,
        576.15,
        576.12,
        576.12,
        576.13,
        576.12,
        576.11,
        575.75,
        575.76,
        575.75,
        575.62,
        575.44,
        575.55,
        575.44,
        575.43,
        575.43,
        575.41,
        575.4,
        575.41,
        575.42,
        575.3,
        575.4,
        575.43,
        575.45,
        575.45,
        575.35,
        575.45,
        575.48,
        575.47,
        575.49,
        575.48,
        575.35,
        575.38,
        575.38,
        575.36,
        575.38,
        575.36,
        575.22,
        575.34,
        575.57,
        575.91,
        575.91,
        575.91
      ],
      "dayLow": 571.03,
      "dayHigh": 576.79,
      "weekLow": 569.97,
      "weekHigh": 576.79,
      "allTimeLow": 569.97,
      "allTimeHigh": 576.79
    },
    "18": {
      "recent": [
        615.42,
        615.43,
        615.41,
        615.21,
        615.2,
        615.14,
        615.14,
        615.1,
        614.94,
        614.93,
        614.96,
        614.9,
        614.95,
        614.94,
        615.05,
        615.07,
        615,
        615,
        614.93,
        615.11,
        615.13,
        615.06,
        615.09,
        615.2,
        614.9,
        614.91,
        614.79,
        614.79,
        614.93,
        614.97,
        614.92,
        614.94,
        614.96,
        615.15,
        615.41,
        615.44,
        615.44,
        615.35,
        615.4,
        615.38,
        615.32,
        615.28,
        615.24,
        615.12,
        615.1,
        615.17,
        615.17,
        614.98,
        614.69,
        615.01,
        615.16,
        615.15,
        615.33,
        615.29,
        615.2,
        615.27,
        615.12,
        615.12,
        615.2,
        615.27,
        615.19,
        615.17,
        615.19,
        615.05,
        615.06,
        615.08,
        615.14,
        615.13,
        615.27,
        615.37,
        615.35,
        615.21,
        615.08,
        614.9,
        614.82,
        614.76,
        614.69,
        614.63,
        614.56,
        614.77,
        614.9,
        615.06,
        615.01,
        614.96,
        614.97,
        615,
        614.97,
        614.98,
        615.06,
        615.07,
        615.15,
        615.04,
        615.07,
        615.04,
        615.05,
        615.07,
        615.03,
        615.01,
        615.02,
        615.07,
        615.04,
        615.07,
        615.03,
        615.01,
        614.7,
        614.7,
        614.77,
        614.74,
        614.75,
        614.82,
        614.83,
        614.74,
        614.73,
        614.78,
        614.87,
        614.86,
        614.91,
        614.9,
        614.92,
        614.94
      ],
      "dayLow": 614.56,
      "dayHigh": 619.48,
      "weekLow": 614.56,
      "weekHigh": 620.25,
      "allTimeLow": 614.56,
      "allTimeHigh": 620.25
    },
    "19": {
      "recent": [
        281.98,
        281.91,
        281.95,
        281.97,
        281.97,
        282.01,
        281.96,
        281.97,
        281.97,
        281.95,
        281.97,
        281.96,
        281.94,
        281.92,
        281.92,
        281.92,
        281.96,
        281.94,
        281.91,
        281.97,
        281.89,
        281.91,
        281.86,
        281.86,
        281.87,
        281.87,
        281.9,
        281.98,
        281.95,
        282.05,
        281.98,
        281.92,
        281.92,
        281.95,
        281.97,
        281.92,
        281.92,
        281.94,
        281.92,
        281.92,
        281.93,
        281.87,
        281.75,
        281.77,
        281.84,
        281.8,
        281.8,
        281.84,
        281.82,
        281.81,
        281.76,
        281.76,
        281.73,
        281.77,
        281.8,
        281.78,
        281.76,
        281.74,
        281.69,
        281.69,
        281.72,
        281.66,
        281.65,
        281.66,
        281.66,
        281.68,
        281.7,
        281.78,
        281.78,
        281.78,
        281.71,
        281.67,
        281.63,
        281.61,
        281.65,
        281.66,
        281.66,
        281.66,
        281.68,
        281.65,
        281.71,
        281.74,
        281.79,
        281.82,
        281.83,
        281.85,
        281.83,
        281.84,
        281.83,
        281.88,
        281.88,
        281.89,
        281.9,
        282.06,
        282.03,
        282,
        282.02,
        282,
        281.94,
        281.91,
        281.98,
        282.02,
        282,
        281.97,
        281.98,
        282.02,
        282,
        281.93,
        281.89,
        281.93,
        281.92,
        281.9,
        281.88,
        281.91,
        281.94,
        281.89,
        281.94,
        281.97,
        282.01,
        281.91
      ],
      "dayLow": 281.61,
      "dayHigh": 282.85,
      "weekLow": 281.61,
      "weekHigh": 283.8,
      "allTimeLow": 281.61,
      "allTimeHigh": 283.8
    },
    "20": {
      "recent": [
        303.49,
        303.49,
        303.45,
        303.39,
        303.43,
        303.42,
        303.47,
        303.44,
        303.44,
        303.46,
        303.46,
        303.54,
        303.41,
        303.36,
        303.36,
        303.42,
        303.48,
        303.43,
        303.4,
        303.33,
        303.32,
        303.28,
        303.28,
        303.28,
        303.27,
        303.34,
        303.3,
        303.29,
        303.29,
        303.22,
        303.19,
        303.22,
        303.2,
        303.18,
        303.27,
        303.23,
        303.24,
        303.29,
        303.33,
        303.38,
        303.52,
        303.55,
        303.46,
        303.43,
        303.42,
        303.46,
        303.44,
        303.47,
        303.44,
        303.45,
        303.42,
        303.42,
        303.44,
        303.42,
        303.46,
        303.56,
        303.41,
        303.39,
        303.32,
        303.35,
        303.35,
        303.35,
        303.35,
        303.37,
        303.25,
        303.27,
        303.32,
        303.28,
        303.24,
        303.3,
        303.35,
        303.32,
        303.3,
        303.31,
        303.33,
        303.33,
        303.25,
        303.28,
        303.35,
        303.32,
        303.42,
        303.46,
        303.49,
        303.54,
        303.57,
        303.53,
        303.51,
        303.51,
        303.45,
        303.47,
        303.46,
        303.46,
        303.39,
        303.4,
        303.4,
        303.43,
        303.39,
        303.39,
        303.4,
        303.4,
        303.48,
        303.42,
        303.42,
        303.43,
        303.43,
        303.44,
        303.43,
        303.46,
        303.49,
        303.57,
        303.59,
        303.58,
        303.58,
        303.62,
        303.65,
        303.61,
        303.62,
        303.61,
        303.67,
        303.72
      ],
      "dayLow": 302.89,
      "dayHigh": 303.8,
      "weekLow": 302.51,
      "weekHigh": 303.8,
      "allTimeLow": 302.51,
      "allTimeHigh": 303.8
    },
    "21": {
      "recent": [
        318.96,
        318.96,
        318.95,
        318.95,
        318.97,
        318.96,
        318.93,
        318.9,
        318.9,
        318.83,
        318.83,
        318.93,
        318.9,
        318.9,
        318.9,
        318.9,
        318.91,
        318.9,
        318.92,
        318.93,
        318.91,
        318.91,
        318.89,
        318.93,
        318.93,
        318.96,
        318.98,
        319.01,
        319.01,
        319.06,
        318.97,
        319,
        319.02,
        318.95,
        318.94,
        318.98,
        318.98,
        319,
        318.95,
        318.95,
        318.98,
        318.97,
        318.94,
        318.95,
        318.96,
        318.84,
        318.83,
        318.83,
        318.78,
        318.79,
        318.78,
        318.75,
        318.73,
        318.78,
        318.75,
        318.79,
        318.81,
        318.91,
        318.94,
        318.97,
        318.96,
        319,
        318.99,
        318.95,
        318.93,
        318.94,
        318.93,
        318.91,
        318.93,
        319.01,
        318.97,
        319.01,
        319.11,
        319.13,
        319.37,
        319.28,
        319.27,
        319.13,
        319.13,
        319.09,
        319.12,
        319.11,
        319.21,
        319.07,
        319.18,
        319.22,
        319.25,
        319.19,
        319.15,
        319.12,
        319.13,
        319.11,
        319.12,
        319.1,
        319.1,
        319.06,
        319.1,
        319.1,
        319.01,
        318.99,
        318.94,
        318.83,
        318.79,
        318.82,
        318.78,
        318.76,
        318.79,
        318.72,
        318.79,
        318.82,
        318.87,
        318.86,
        318.87,
        318.83,
        318.82,
        318.81,
        318.98,
        319,
        318.98,
        318.99
      ],
      "dayLow": 318.38,
      "dayHigh": 320.19,
      "weekLow": 318.38,
      "weekHigh": 321.08,
      "allTimeLow": 318.38,
      "allTimeHigh": 321.08
    },
    "22": {
      "recent": [
        266.11,
        266.13,
        266.18,
        266.14,
        266.19,
        266.22,
        266.25,
        266.23,
        266.27,
        266.24,
        266.24,
        266.29,
        266.33,
        266.3,
        266.27,
        266.21,
        266.22,
        266.21,
        266.21,
        266.2,
        266.23,
        266.21,
        266.21,
        266.2,
        266.21,
        266.18,
        266.17,
        266.18,
        266.13,
        266.12,
        266.07,
        266.05,
        266.04,
        266.08,
        266.09,
        266.08,
        266.08,
        266.05,
        266.06,
        266.03,
        266.05,
        266.04,
        266.1,
        266.11,
        266.08,
        266.1,
        266.09,
        266.07,
        266.08,
        266.05,
        266.01,
        265.98,
        266,
        265.95,
        265.99,
        265.99,
        265.99,
        265.97,
        265.95,
        265.94,
        265.92,
        265.93,
        265.89,
        265.82,
        265.84,
        265.9,
        265.81,
        265.81,
        265.8,
        265.77,
        265.84,
        265.82,
        265.78,
        265.75,
        265.82,
        265.8,
        265.7,
        265.67,
        265.75,
        265.71,
        265.75,
        265.73,
        265.76,
        265.76,
        265.71,
        265.69,
        265.65,
        265.72,
        265.73,
        265.8,
        265.85,
        265.8,
        265.73,
        265.72,
        265.71,
        265.74,
        265.74,
        265.74,
        265.74,
        265.71,
        265.64,
        265.59,
        265.64,
        265.58,
        265.64,
        265.68,
        265.66,
        265.67,
        265.67,
        265.7,
        265.75,
        265.73,
        265.78,
        265.79,
        265.75,
        265.75,
        265.72,
        265.73,
        265.77,
        265.74
      ],
      "dayLow": 265.58,
      "dayHigh": 267.79,
      "weekLow": 265.58,
      "weekHigh": 267.79,
      "allTimeLow": 265.58,
      "allTimeHigh": 267.79
    },
    "23": {
      "recent": [
        145.73,
        145.74,
        145.77,
        145.78,
        145.79,
        145.76,
        145.76,
        145.77,
        145.75,
        145.75,
        145.76,
        145.79,
        145.8,
        145.82,
        145.77,
        145.76,
        145.76,
        145.75,
        145.71,
        145.68,
        145.69,
        145.68,
        145.71,
        145.69,
        145.67,
        145.7,
        145.74,
        145.72,
        145.73,
        145.74,
        145.74,
        145.75,
        145.77,
        145.75,
        145.68,
        145.73,
        145.71,
        145.73,
        145.71,
        145.7,
        145.69,
        145.7,
        145.71,
        145.71,
        145.69,
        145.71,
        145.7,
        145.7,
        145.69,
        145.7,
        145.69,
        145.71,
        145.72,
        145.73,
        145.71,
        145.72,
        145.71,
        145.7,
        145.67,
        145.7,
        145.65,
        145.6,
        145.59,
        145.57,
        145.54,
        145.57,
        145.56,
        145.55,
        145.56,
        145.57,
        145.6,
        145.59,
        145.61,
        145.64,
        145.64,
        145.65,
        145.64,
        145.64,
        145.66,
        145.65,
        145.7,
        145.71,
        145.74,
        145.72,
        145.74,
        145.74,
        145.75,
        145.73,
        145.68,
        145.67,
        145.62,
        145.58,
        145.59,
        145.62,
        145.6,
        145.6,
        145.6,
        145.6,
        145.57,
        145.55,
        145.56,
        145.57,
        145.59,
        145.57,
        145.52,
        145.51,
        145.5,
        145.5,
        145.5,
        145.49,
        145.51,
        145.5,
        145.53,
        145.54,
        145.54,
        145.54,
        145.58,
        145.54,
        145.52,
        145.57
      ],
      "dayLow": 145.04,
      "dayHigh": 145.84,
      "weekLow": 144.91,
      "weekHigh": 145.84,
      "allTimeLow": 144.91,
      "allTimeHigh": 145.84
    },
    "24": {
      "recent": [
        553.84,
        553.69,
        553.56,
        553.45,
        553.46,
        553.39,
        553.43,
        553.46,
        553.35,
        553.38,
        553.34,
        553.49,
        553.41,
        553.34,
        553.41,
        553.45,
        553.4,
        553.5,
        553.5,
        553.36,
        553.53,
        553.53,
        553.48,
        553.47,
        553.47,
        553.41,
        553.5,
        553.36,
        553.4,
        553.36,
        553.4,
        553.36,
        553.28,
        553.36,
        553.27,
        553.23,
        553.16,
        553.19,
        553.22,
        553.25,
        553.27,
        553.27,
        553.4,
        553.41,
        553.4,
        553.37,
        553.33,
        553.27,
        553.27,
        553.16,
        553.29,
        553.16,
        553.1,
        553.03,
        553.19,
        553.22,
        553.25,
        553.35,
        553.35,
        553.42,
        553.44,
        553.43,
        553.39,
        553.36,
        553.34,
        553.38,
        553.38,
        553.32,
        553.32,
        553.34,
        553.41,
        553.35,
        553.32,
        553.38,
        553.36,
        553.26,
        553.29,
        553.29,
        553.36,
        553.39,
        553.35,
        553.38,
        553.36,
        553.43,
        553.43,
        553.5,
        553.34,
        553.31,
        553.23,
        553.24,
        553.28,
        553.37,
        553.37,
        553.37,
        553.37,
        553.44,
        553.53,
        553.57,
        553.59,
        553.6,
        553.63,
        553.7,
        553.7,
        553.74,
        553.74,
        553.66,
        553.58,
        553.58,
        553.58,
        553.58,
        553.57,
        553.67,
        553.61,
        553.7,
        553.67,
        553.7,
        553.74,
        553.63,
        553.69,
        553.64
      ],
      "dayLow": 551.85,
      "dayHigh": 554.38,
      "weekLow": 551.85,
      "weekHigh": 554.38,
      "allTimeLow": 551.85,
      "allTimeHigh": 554.38
    },
    "25": {
      "recent": [
        106.82,
        106.83,
        106.83,
        106.85,
        106.87,
        106.87,
        106.84,
        106.8,
        106.78,
        106.78,
        106.78,
        106.8,
        106.8,
        106.8,
        106.77,
        106.75,
        106.74,
        106.75,
        106.75,
        106.76,
        106.73,
        106.72,
        106.73,
        106.75,
        106.75,
        106.75,
        106.76,
        106.75,
        106.7,
        106.73,
        106.73,
        106.75,
        106.75,
        106.75,
        106.75,
        106.72,
        106.72,
        106.69,
        106.7,
        106.71,
        106.68,
        106.71,
        106.7,
        106.7,
        106.7,
        106.7,
        106.7,
        106.69,
        106.69,
        106.7,
        106.7,
        106.7,
        106.71,
        106.7,
        106.71,
        106.71,
        106.69,
        106.72,
        106.72,
        106.72,
        106.72,
        106.73,
        106.74,
        106.7,
        106.69,
        106.69,
        106.7,
        106.69,
        106.64,
        106.6,
        106.58,
        106.59,
        106.61,
        106.61,
        106.61,
        106.62,
        106.62,
        106.63,
        106.61,
        106.64,
        106.65,
        106.64,
        106.65,
        106.65,
        106.65,
        106.66,
        106.67,
        106.63,
        106.64,
        106.63,
        106.65,
        106.64,
        106.65,
        106.58,
        106.62,
        106.61,
        106.56,
        106.56,
        106.55,
        106.54,
        106.54,
        106.53,
        106.56,
        106.53,
        106.52,
        106.53,
        106.55,
        106.56,
        106.58,
        106.56,
        106.55,
        106.53,
        106.53,
        106.56,
        106.52,
        106.57,
        106.59,
        106.57,
        106.57,
        106.61
      ],
      "dayLow": 106.52,
      "dayHigh": 107.28,
      "weekLow": 106.52,
      "weekHigh": 107.39,
      "allTimeLow": 106.52,
      "allTimeHigh": 107.39
    },
    "26": {
      "recent": [
        527.84,
        527.83,
        527.81,
        527.82,
        527.83,
        527.89,
        527.86,
        527.78,
        527.76,
        527.84,
        527.77,
        527.88,
        527.86,
        527.95,
        527.94,
        527.93,
        527.91,
        527.89,
        527.93,
        527.9,
        527.91,
        527.84,
        527.86,
        527.83,
        527.88,
        527.96,
        528,
        528,
        528.01,
        528.04,
        528,
        528.01,
        528.01,
        528.04,
        528.04,
        528.02,
        528.02,
        528.06,
        528.04,
        528.05,
        528.08,
        528.12,
        528.08,
        528.09,
        528.2,
        528.14,
        528.19,
        528.22,
        528.25,
        528.24,
        528.32,
        528.33,
        528.32,
        528.27,
        528.39,
        528.33,
        528.33,
        528.36,
        528.29,
        528.3,
        528.37,
        528.38,
        528.51,
        528.56,
        528.55,
        528.48,
        528.64,
        528.67,
        528.61,
        528.66,
        528.71,
        528.63,
        528.6,
        528.61,
        528.61,
        528.53,
        528.43,
        528.35,
        528.35,
        528.39,
        528.36,
        528.36,
        528.39,
        528.53,
        528.47,
        528.47,
        528.5,
        528.45,
        528.46,
        528.48,
        528.55,
        528.55,
        528.51,
        528.52,
        528.59,
        528.52,
        528.5,
        528.48,
        528.39,
        528.42,
        528.39,
        528.4,
        528.6,
        528.65,
        528.82,
        528.76,
        528.69,
        528.74,
        528.71,
        528.75,
        528.65,
        528.67,
        528.71,
        528.79,
        528.84,
        528.92,
        528.99,
        528.99,
        529.06,
        529.01
      ],
      "dayLow": 527.28,
      "dayHigh": 529.06,
      "weekLow": 527.28,
      "weekHigh": 529.41,
      "allTimeLow": 527.28,
      "allTimeHigh": 529.41
    },
    "27": {
      "recent": [
        479.1,
        479.11,
        479.12,
        479.08,
        479.11,
        479.12,
        479.16,
        479.2,
        479.32,
        479.43,
        479.47,
        479.36,
        479.34,
        479.42,
        479.4,
        479.37,
        479.45,
        479.57,
        479.64,
        479.59,
        479.72,
        479.74,
        479.83,
        479.85,
        479.93,
        479.91,
        479.89,
        479.98,
        479.92,
        479.91,
        480.09,
        480.32,
        480.31,
        480.06,
        480.03,
        480.1,
        480.11,
        480.14,
        480.11,
        479.91,
        479.94,
        480.11,
        480.07,
        479.94,
        480.2,
        480.14,
        480.14,
        480.1,
        480.09,
        480.19,
        480.07,
        480.13,
        480.11,
        480.16,
        480.17,
        480.2,
        480.19,
        480.13,
        480.04,
        480.03,
        480.01,
        479.93,
        480,
        479.95,
        479.94,
        479.83,
        479.87,
        479.78,
        479.74,
        479.71,
        479.73,
        479.6,
        479.66,
        479.63,
        479.4,
        479.28,
        479.28,
        479.25,
        479.11,
        479.29,
        479.16,
        478.92,
        478.83,
        478.81,
        478.82,
        478.86,
        478.83,
        478.77,
        478.74,
        478.69,
        478.7,
        478.78,
        478.73,
        478.66,
        478.64,
        478.72,
        478.76,
        478.81,
        478.95,
        478.91,
        478.9,
        478.59,
        478.47,
        478.35,
        478.37,
        478.41,
        478.27,
        478.38,
        478.3,
        478.26,
        478.2,
        478.26,
        478.22,
        478.25,
        478.25,
        478.31,
        478.43,
        478.66,
        478.5,
        478.47
      ],
      "dayLow": 478.2,
      "dayHigh": 481.83,
      "weekLow": 478.2,
      "weekHigh": 482.86,
      "allTimeLow": 478.2,
      "allTimeHigh": 482.86
    },
    "28": {
      "recent": [
        632.62,
        632.69,
        632.61,
        632.73,
        632.68,
        632.7,
        632.62,
        632.6,
        632.57,
        632.63,
        632.68,
        632.68,
        632.52,
        632.26,
        632.3,
        632.41,
        632.45,
        632.43,
        632.45,
        632.3,
        632.36,
        632.4,
        632.25,
        632.36,
        632.37,
        632.25,
        632.32,
        632.18,
        632.25,
        632.22,
        632.35,
        632.35,
        632.35,
        632.4,
        632.23,
        632.31,
        632.32,
        632.3,
        632.26,
        632.23,
        632.27,
        632.21,
        632.11,
        631.93,
        631.9,
        631.9,
        631.87,
        631.91,
        631.83,
        631.76,
        631.8,
        631.77,
        631.91,
        631.97,
        631.96,
        631.92,
        631.75,
        631.79,
        631.91,
        631.87,
        631.94,
        631.93,
        631.95,
        631.91,
        631.87,
        632,
        632.03,
        632.09,
        632.09,
        632.08,
        632.13,
        632.16,
        632.18,
        632.2,
        632.12,
        632.11,
        632.09,
        632.05,
        632.03,
        632.04,
        632.02,
        631.93,
        631.9,
        631.84,
        631.93,
        631.89,
        631.9,
        631.91,
        631.95,
        631.82,
        631.86,
        631.9,
        631.95,
        631.98,
        631.9,
        632,
        631.94,
        631.85,
        631.89,
        632.02,
        632.08,
        631.95,
        631.94,
        632.03,
        632.03,
        631.98,
        632.07,
        632.08,
        632.06,
        631.95,
        631.95,
        631.87,
        631.91,
        631.89,
        631.89,
        631.9,
        631.93,
        631.8,
        631.78,
        631.85
      ],
      "dayLow": 631.75,
      "dayHigh": 634.42,
      "weekLow": 631.75,
      "weekHigh": 636.68,
      "allTimeLow": 631.75,
      "allTimeHigh": 636.68
    },
    "29": {
      "recent": [
        800.64,
        800.6,
        800.61,
        800.33,
        800.29,
        800.23,
        800.18,
        800.04,
        799.93,
        800,
        799.97,
        800.11,
        800,
        799.97,
        799.91,
        799.83,
        799.76,
        799.65,
        799.84,
        799.88,
        799.79,
        799.61,
        799.67,
        799.66,
        799.34,
        799.64,
        799.59,
        799.42,
        799.46,
        799.46,
        799.34,
        799.39,
        799.55,
        799.42,
        799.44,
        799.75,
        799.49,
        799.53,
        799.33,
        799.21,
        799.21,
        799.21,
        799.28,
        799.09,
        799.17,
        799.08,
        798.89,
        798.74,
        798.77,
        798.65,
        798.7,
        798.81,
        798.81,
        798.85,
        798.74,
        798.85,
        798.85,
        799.17,
        799.4,
        799.44,
        799.56,
        799.56,
        799.64,
        799.49,
        799.45,
        799.49,
        799.3,
        798.99,
        799.07,
        799.03,
        798.98,
        799.02,
        799.17,
        799.33,
        799.29,
        799.29,
        799.29,
        799.14,
        799.26,
        799.38,
        799.49,
        799.3,
        799.3,
        799.22,
        799.17,
        798.94,
        798.91,
        798.87,
        798.95,
        798.95,
        799.03,
        798.75,
        798.6,
        798.64,
        798.52,
        798.49,
        798.45,
        798.45,
        798.49,
        798.53,
        798.57,
        798.65,
        798.69,
        798.69,
        798.61,
        798.61,
        798.69,
        798.69,
        798.69,
        798.65,
        798.57,
        798.68,
        798.68,
        798.8,
        798.72,
        798.72,
        798.76,
        798.84,
        798.92,
        798.84
      ],
      "dayLow": 798.45,
      "dayHigh": 803.01,
      "weekLow": 798.45,
      "weekHigh": 803.01,
      "allTimeLow": 798.45,
      "allTimeHigh": 803.01
    },
    "30": {
      "recent": [
        766.75,
        766.77,
        766.71,
        766.76,
        766.51,
        766.5,
        766.58,
        766.49,
        766.4,
        766.37,
        766.38,
        766.43,
        766.28,
        766.31,
        766.23,
        766.22,
        766.27,
        765.98,
        766.01,
        766.01,
        766.16,
        766.15,
        766,
        765.97,
        765.99,
        765.86,
        765.67,
        765.79,
        765.81,
        765.67,
        765.83,
        765.97,
        766.1,
        765.83,
        766.1,
        766.13,
        766.26,
        765.85,
        765.98,
        765.99,
        765.67,
        765.98,
        765.9,
        765.97,
        766.06,
        765.96,
        766.04,
        765.99,
        765.86,
        765.86,
        765.81,
        765.63,
        765.64,
        765.6,
        765.66,
        765.67,
        765.79,
        765.79,
        765.94,
        765.95,
        765.87,
        765.78,
        765.79,
        765.74,
        765.66,
        765.68,
        765.82,
        765.97,
        765.82,
        765.88,
        765.95,
        765.94,
        765.88,
        765.94,
        765.81,
        765.71,
        765.77,
        765.78,
        765.91,
        765.77,
        765.9,
        765.9,
        765.98,
        766.03,
        765.93,
        765.94,
        765.96,
        766.06,
        766.06,
        766.09,
        766.02,
        766.01,
        766.01,
        765.93,
        765.79,
        765.79,
        765.39,
        765.25,
        765.28,
        765.11,
        765.24,
        765.12,
        765.1,
        764.98,
        764.97,
        765.12,
        765.12,
        765.05,
        765.27,
        765.34,
        765.48,
        765.37,
        765.48,
        765.45,
        765.46,
        765.2,
        765.2,
        765.43,
        765.43,
        765.44
      ],
      "dayLow": 764.97,
      "dayHigh": 770.38,
      "weekLow": 764.97,
      "weekHigh": 772.2,
      "allTimeLow": 764.97,
      "allTimeHigh": 772.2
    },
    "31": {
      "recent": [
        508.87,
        508.83,
        508.81,
        508.89,
        508.87,
        508.87,
        508.85,
        508.88,
        508.87,
        508.92,
        508.92,
        508.92,
        508.91,
        508.84,
        508.91,
        508.93,
        508.92,
        509.07,
        509.13,
        509.05,
        509.17,
        509.09,
        509.1,
        509.06,
        509.01,
        509.05,
        509.08,
        509.05,
        509.08,
        509.16,
        509.06,
        509.01,
        509,
        509.1,
        509.04,
        508.99,
        509.01,
        508.92,
        508.94,
        508.94,
        508.97,
        509.05,
        508.95,
        508.99,
        508.84,
        508.84,
        508.78,
        508.78,
        508.78,
        508.86,
        508.74,
        508.83,
        508.78,
        508.77,
        508.65,
        508.72,
        508.71,
        508.77,
        508.79,
        508.8,
        508.79,
        508.79,
        508.81,
        508.77,
        508.76,
        508.7,
        508.68,
        508.72,
        508.69,
        508.65,
        508.63,
        508.65,
        508.95,
        508.99,
        508.9,
        508.95,
        508.97,
        509.01,
        509.03,
        508.92,
        509.05,
        509.03,
        509.03,
        509.03,
        508.92,
        509.01,
        508.96,
        508.88,
        508.88,
        508.9,
        508.88,
        508.9,
        509.01,
        509.03,
        509.14,
        509.1,
        509,
        508.97,
        508.94,
        508.98,
        508.96,
        508.96,
        508.83,
        508.83,
        508.88,
        508.85,
        508.93,
        508.89,
        508.91,
        508.96,
        508.91,
        508.91,
        508.93,
        508.82,
        508.85,
        508.8,
        508.76,
        508.74,
        508.72,
        508.63
      ],
      "dayLow": 508.63,
      "dayHigh": 511.74,
      "weekLow": 508.63,
      "weekHigh": 513.19,
      "allTimeLow": 508.63,
      "allTimeHigh": 513.19
    },
    "32": {
      "recent": [
        345.2,
        345.1,
        345.05,
        345.13,
        345.13,
        345.21,
        345.16,
        345.17,
        345.18,
        345.16,
        345.08,
        345.08,
        345.13,
        345.11,
        345.1,
        345.23,
        345.28,
        345.28,
        345.28,
        345.25,
        345.23,
        345.25,
        345.06,
        345.08,
        345.04,
        345.07,
        345.1,
        345.15,
        345.24,
        345.3,
        345.33,
        345.35,
        345.36,
        345.36,
        345.24,
        345.15,
        345.13,
        345.25,
        345.16,
        345.12,
        345.08,
        345.1,
        344.94,
        345,
        345.09,
        345.09,
        345.16,
        345.17,
        345.14,
        345.16,
        345.18,
        345.14,
        345.19,
        345.18,
        345.2,
        345.17,
        345.07,
        344.98,
        344.85,
        344.7,
        344.64,
        344.58,
        344.48,
        344.49,
        344.41,
        344.35,
        344.31,
        344.28,
        344.23,
        344.23,
        344.19,
        344.21,
        344.18,
        344.19,
        344.24,
        344.22,
        344.25,
        344.25,
        344.24,
        344.25,
        344.08,
        344.1,
        344.1,
        344.05,
        344.14,
        344.15,
        344.13,
        344.1,
        344.11,
        344.13,
        344.26,
        344.29,
        344.28,
        344.33,
        344.36,
        344.39,
        344.52,
        344.57,
        344.36,
        344.39,
        344.43,
        344.26,
        344.32,
        344.29,
        344.31,
        344.29,
        344.29,
        344.21,
        344.28,
        344.37,
        344.35,
        344.32,
        344.34,
        344.33,
        344.33,
        344.36,
        344.33,
        344.34,
        344.35,
        344.28
      ],
      "dayLow": 343.78,
      "dayHigh": 346.8,
      "weekLow": 343.78,
      "weekHigh": 346.8,
      "allTimeLow": 343.78,
      "allTimeHigh": 346.8
    },
    "33": {
      "recent": [
        390.93,
        391.02,
        390.99,
        391.07,
        391.03,
        391.06,
        391.17,
        391.24,
        391.12,
        391.12,
        391.1,
        391.01,
        391,
        390.95,
        390.85,
        390.9,
        390.89,
        390.92,
        390.87,
        390.86,
        390.73,
        390.73,
        390.57,
        390.52,
        390.53,
        390.57,
        390.62,
        390.52,
        390.51,
        390.63,
        390.67,
        390.62,
        390.68,
        390.67,
        390.64,
        390.69,
        390.64,
        390.65,
        390.6,
        390.52,
        390.54,
        390.47,
        390.52,
        390.51,
        390.6,
        390.63,
        390.57,
        390.75,
        390.86,
        390.9,
        390.8,
        390.81,
        390.84,
        390.93,
        390.82,
        390.86,
        390.83,
        390.91,
        390.89,
        390.89,
        391.01,
        391.15,
        391.21,
        391.12,
        391.09,
        391.21,
        391.21,
        391.32,
        391.29,
        391.17,
        391.15,
        391.18,
        391.31,
        391.3,
        391.17,
        391.1,
        391.03,
        391.02,
        390.96,
        391.03,
        391.03,
        390.99,
        391.03,
        391.09,
        391.05,
        391.12,
        391.19,
        391.3,
        391.44,
        391.45,
        391.52,
        391.52,
        391.55,
        391.48,
        391.5,
        391.75,
        391.77,
        391.68,
        391.72,
        391.89,
        391.78,
        391.69,
        391.74,
        391.7,
        391.66,
        391.73,
        391.71,
        391.69,
        391.73,
        391.68,
        391.69,
        391.65,
        391.62,
        391.56,
        391.63,
        391.7,
        391.61,
        391.7,
        391.65,
        391.66
      ],
      "dayLow": 390.47,
      "dayHigh": 392.71,
      "weekLow": 389.47,
      "weekHigh": 392.71,
      "allTimeLow": 389.47,
      "allTimeHigh": 392.71
    },
    "34": {
      "recent": [
        109.06,
        109.06,
        109.06,
        109.07,
        109.05,
        109.04,
        109.02,
        109.03,
        109.04,
        109.03,
        109.04,
        109.08,
        109.08,
        109.08,
        109.1,
        109.12,
        109.11,
        109.11,
        109.13,
        109.14,
        109.13,
        109.14,
        109.17,
        109.18,
        109.18,
        109.17,
        109.16,
        109.18,
        109.18,
        109.18,
        109.15,
        109.17,
        109.17,
        109.18,
        109.19,
        109.2,
        109.17,
        109.18,
        109.17,
        109.19,
        109.16,
        109.19,
        109.2,
        109.18,
        109.18,
        109.2,
        109.2,
        109.18,
        109.21,
        109.19,
        109.19,
        109.21,
        109.22,
        109.21,
        109.23,
        109.21,
        109.21,
        109.22,
        109.2,
        109.19,
        109.19,
        109.18,
        109.15,
        109.15,
        109.13,
        109.12,
        109.13,
        109.13,
        109.15,
        109.14,
        109.14,
        109.13,
        109.11,
        109.13,
        109.13,
        109.15,
        109.14,
        109.13,
        109.14,
        109.15,
        109.13,
        109.14,
        109.13,
        109.13,
        109.13,
        109.14,
        109.12,
        109.11,
        109.11,
        109.11,
        109.1,
        109.09,
        109.08,
        109.07,
        109.08,
        109.08,
        109.11,
        109.1,
        109.13,
        109.12,
        109.12,
        109.12,
        109.1,
        109.1,
        109.1,
        109.09,
        109.11,
        109.12,
        109.14,
        109.14,
        109.11,
        109.15,
        109.11,
        109.13,
        109.11,
        109.11,
        109.1,
        109.1,
        109.11,
        109.09
      ],
      "dayLow": 108.8,
      "dayHigh": 109.24,
      "weekLow": 108.8,
      "weekHigh": 109.61,
      "allTimeLow": 108.8,
      "allTimeHigh": 109.61
    },
    "35": {
      "recent": [
        75.55,
        75.57,
        75.57,
        75.57,
        75.56,
        75.56,
        75.56,
        75.56,
        75.56,
        75.56,
        75.56,
        75.56,
        75.56,
        75.56,
        75.56,
        75.56,
        75.56,
        75.56,
        75.56,
        75.56,
        75.58,
        75.58,
        75.58,
        75.64,
        75.64,
        75.65,
        75.68,
        75.71,
        75.71,
        75.7,
        75.71,
        75.71,
        75.7,
        75.7,
        75.7,
        75.66,
        75.66,
        75.67,
        75.67,
        75.67,
        75.63,
        75.63,
        75.64,
        75.64,
        75.63,
        75.63,
        75.61,
        75.63,
        75.65,
        75.65,
        75.66,
        75.67,
        75.67,
        75.7,
        75.74,
        75.76,
        75.76,
        75.77,
        75.76,
        75.77,
        75.73,
        75.73,
        75.75,
        75.74,
        75.74,
        75.74,
        75.73,
        75.71,
        75.73,
        75.73,
        75.71,
        75.66,
        75.68,
        75.66,
        75.67,
        75.67,
        75.67,
        75.67,
        75.67,
        75.67,
        75.67,
        75.67,
        75.68,
        75.68,
        75.68,
        75.69,
        75.71,
        75.7,
        75.7,
        75.7,
        75.7,
        75.7,
        75.7,
        75.7,
        75.71,
        75.71,
        75.7,
        75.7,
        75.7,
        75.67,
        75.66,
        75.65,
        75.65,
        75.65,
        75.63,
        75.64,
        75.64,
        75.61,
        75.62,
        75.62,
        75.66,
        75.66,
        75.64,
        75.65,
        75.65,
        75.65,
        75.66,
        75.65,
        75.65,
        75.65
      ],
      "dayLow": 75.52,
      "dayHigh": 75.8,
      "weekLow": 75.43,
      "weekHigh": 75.8,
      "allTimeLow": 75.43,
      "allTimeHigh": 75.8
    }
  },
  "lastUpdated": 1766185440642,
  "lastAlert": {},
  "_day": "Fri Dec 19 2025",
  "_week": "2025-11",
  "_sha": "cd33367a1759191882bfd2a7998ae0eea5bc1f05"
}